edc_model/__init__.py
edc_model/apps.py
edc_model/choices.py
edc_model/constants.py
edc_model/stubs.py
edc_model/system_checks.py
edc_model/utils.py
edc_model/models/__init__.py
edc_model/models/address_mixin.py
edc_model/models/base_model.py
edc_model/models/base_uuid_model.py
edc_model/models/historical_records.py
edc_model/models/name_fields_model_mixin.py
edc_model/models/report_status_model_mixin.py
edc_model/models/signals.py
edc_model/models/url_model_mixin.py
edc_model/models/fields/__init__.py
edc_model/models/fields/date_estimated.py
edc_model/models/fields/duration.py
edc_model/models/fields/hostname_modification_field.py
edc_model/models/fields/identity_type_field.py
edc_model/models/fields/initials_field.py
edc_model/models/fields/other_charfield.py
edc_model/models/fields/userfield.py
edc_model/static/edc_model/slider.css
edc_model/static/edc_model/slider.png
edc_model/templates/edc_model/widgets/slider.html
edc_model/tests/__init__.py
edc_model/tests/admin_site.py
edc_model/tests/models.py
edc_model/tests/test_settings.py
edc_model/tests/urls.py
edc_model/tests/etc/user-aes-local.key
edc_model/tests/etc/user-aes-restricted.key
edc_model/tests/etc/user-rsa-local-private.pem
edc_model/tests/etc/user-rsa-local-public.pem
edc_model/tests/etc/user-rsa-restricted-private.pem
edc_model/tests/etc/user-rsa-restricted-public.pem
edc_model/tests/etc/user-salt-local.key
edc_model/tests/etc/user-salt-restricted.key
edc_model/tests/tests/__init__.py
edc_model/tests/tests/test_history.py
edc_model/tests/tests/test_models.py
edc_model/tests/tests/test_utils.py
edc_model/tests/tests/test_validators.py
edc_model/validators/__init__.py
edc_model/validators/date.py
edc_model/validators/duration.py
edc_model/validators/phone.py
edc_model/widgets/__init__.py
edc_model/widgets/slider_widget.py
edc_model-1.0.0.dist-info/AUTHORS
edc_model-1.0.0.dist-info/LICENSE
edc_model-1.0.0.dist-info/METADATA
edc_model-1.0.0.dist-info/WHEEL
edc_model-1.0.0.dist-info/top_level.txt
edc_model-1.0.0.dist-info/RECORD
